livellm/__init__.py
livellm/livellm.py
livellm/py.typed
livellm/transcripton.py
livellm/models/__init__.py
livellm/models/common.py
livellm/models/fallback.py
livellm/models/transcription.py
livellm/models/ws.py
livellm/models/agent/__init__.py
livellm/models/agent/agent.py
livellm/models/agent/chat.py
livellm/models/agent/tools.py
livellm/models/audio/__init__.py
livellm/models/audio/speak.py
livellm/models/audio/transcribe.py
livellm-1.5.5.dist-info/METADATA
livellm-1.5.5.dist-info/WHEEL
livellm-1.5.5.dist-info/licenses/LICENSE
livellm-1.5.5.dist-info/RECORD
