Metadata-Version: 2.4
Name: livellm
Version: 1.5.5
Summary: Python client for the LiveLLM Server
Project-URL: Homepage, https://github.com/qalby-tech/livellm-client-py
Project-URL: Repository, https://github.com/qalby-tech/livellm-client-py
Author: Kamil Saliamov
License-File: LICENSE
Classifier: Development Status :: 3 - Alpha
Classifier: Intended Audience :: Developers
Classifier: License :: OSI Approved :: MIT License
Classifier: Programming Language :: Python :: 3
Classifier: Programming Language :: Python :: 3.10
Classifier: Programming Language :: Python :: 3.11
Classifier: Programming Language :: Python :: 3.12
Classifier: Typing :: Typed
Requires-Python: >=3.10
Requires-Dist: httpx>=0.27.0
Requires-Dist: pydantic>=2.0.0
Requires-Dist: sounddevice>=0.5.3
Requires-Dist: websockets>=15.0.1
Provides-Extra: testing
Requires-Dist: pytest-asyncio>=0.21.0; extra == 'testing'
Requires-Dist: pytest-cov>=4.1.0; extra == 'testing'
Requires-Dist: pytest>=8.4.2; extra == 'testing'
